CHANGES.txt
COPYRIGHT.txt
LICENSE.txt
README.txt
ez_setup.py
setup.py
Products/__init__.py
Products.plone_gs.egg-info/PKG-INFO
Products.plone_gs.egg-info/SOURCES.txt
Products.plone_gs.egg-info/dependency_links.txt
Products.plone_gs.egg-info/entry_points.txt
Products.plone_gs.egg-info/namespace_packages.txt
Products.plone_gs.egg-info/not-zip-safe
Products.plone_gs.egg-info/top_level.txt
Products/plone_gs/README.txt
Products/plone_gs/TODO.txt
Products/plone_gs/__init__.py
Products/plone_gs/configure.zcml
Products/plone_gs/interfaces.py
Products/plone_gs/setuphandlers.py
Products/plone_gs/utils.py
Products/plone_gs/archetypes/__init__.py
Products/plone_gs/archetypes/configure.zcml
Products/plone_gs/archetypes/interfaces.py
Products/plone_gs/archetypes/setuphandlers.py
Products/plone_gs/atcontenttypes/__init__.py
Products/plone_gs/atcontenttypes/configure.zcml
Products/plone_gs/atcontenttypes/interfaces.py
Products/plone_gs/atcontenttypes/setuphandlers.py
Products/plone_gs/cmfcalendar/__init__.py
Products/plone_gs/cmfcalendar/configure.zcml
Products/plone_gs/cmfcalendar/interfaces.py
Products/plone_gs/cmfcalendar/setuphandlers.py
Products/plone_gs/cmfdefault/__init__.py
Products/plone_gs/cmfdefault/configure.zcml
Products/plone_gs/cmfdefault/interfaces.py
Products/plone_gs/cmfdefault/setuphandlers.py
Products/plone_gs/cmfplone/__init__.py
Products/plone_gs/cmfplone/configure.zcml
Products/plone_gs/cmfplone/interfaces.py
Products/plone_gs/cmfplone/setuphandlers.py
Products/plone_gs/kupu/__init__.py
Products/plone_gs/kupu/configure.zcml
Products/plone_gs/kupu/interfaces.py
Products/plone_gs/kupu/setuphandlers.py
Products/plone_gs/mimetypesregistry/__init__.py
Products/plone_gs/mimetypesregistry/configure.zcml
Products/plone_gs/mimetypesregistry/interfaces.py
Products/plone_gs/mimetypesregistry/setuphandlers.py
Products/plone_gs/plonepas/__init__.py
Products/plone_gs/plonepas/configure.zcml
Products/plone_gs/plonepas/interfaces.py
Products/plone_gs/plonepas/setuphandlers.py
Products/plone_gs/portaltransforms/__init__.py
Products/plone_gs/portaltransforms/configure.zcml
Products/plone_gs/portaltransforms/interfaces.py
Products/plone_gs/portaltransforms/setuphandlers.py
Products/plone_gs/profiles/baseline/actionicons.xml
