Metadata-Version: 1.0
Name: Products.plone-gs
Version: 0.3.1
Summary: GenericSetup support for Plone
Home-page: http://agendaless.com/software/plone_gs
Author: Tres Seaver, Agendaless Consulting
Author-email: tseaver@agendaless.com
License: ZPL
Platform: UNKNOWN
